flake8_spm/__init__.py
flake8_spm/plugin.py
flake8_spm/visitors/__init__.py
flake8_spm/visitors/match_default.py
flake8_spm-0.0.1.dist-info/METADATA
flake8_spm-0.0.1.dist-info/WHEEL
flake8_spm-0.0.1.dist-info/entry_points.txt
flake8_spm-0.0.1.dist-info/licenses/LICENSE
flake8_spm-0.0.1.dist-info/RECORD
