Metadata-Version: 2.4
Name: flake8-spm
Version: 0.0.1
Summary: Flake8 plugin for structural pattern matching
Project-URL: Homepage, https://github.com/ivanovmg/flake8-spm
Project-URL: Issues, https://github.com/ivanovmg/flake8-spm/issues
Author-email: Maxim Ivanov <ivanovmg@gmail.com>
License-File: LICENSE
Classifier: Development Status :: 2 - Pre-Alpha
Classifier: Framework :: Flake8
Classifier: Intended Audience :: Developers
Classifier: License :: OSI Approved :: MIT License
Classifier: Operating System :: OS Independent
Classifier: Programming Language :: Python :: 3
Classifier: Programming Language :: Python :: 3.10
Classifier: Programming Language :: Python :: 3.11
Classifier: Programming Language :: Python :: 3.12
Classifier: Programming Language :: Python :: 3.13
Requires-Python: >=3.10
